tests/__init__.py
tests/test_containers.py
tests/test_integrations.py
tests/test_jobs.py
tests/test_lsf.py
tests/test_parsers.py
tests/test_utils.py
tests/test_version.py
tests/utils.py
toil_container/VERSION
toil_container/__init__.py
toil_container/containers.py
toil_container/exceptions.py
toil_container/jobs.py
toil_container/lsf.py
toil_container/lsf_helper.py
toil_container/parsers.py
toil_container/utils.py
toil_container/validators.py
toil_container-2.0.3.dist-info/LICENSE
toil_container-2.0.3.dist-info/METADATA
toil_container-2.0.3.dist-info/WHEEL
toil_container-2.0.3.dist-info/top_level.txt
toil_container-2.0.3.dist-info/RECORD
