Metadata-Version: 2.1
Name: toil-container
Version: 2.0.3
Summary: A python package with a Toil Job Class capable of containerized system calls.
Home-page: https://github.com/papaemmelab/toil_container
Author: Juan S. Medina, Juan E. Arango
Author-email: <medinaj@mskcc.org>, <arangooj@mskk.org>
License: MIT license
Keywords: toil_container,toil,docker,singularity
Platform: UNKNOWN
Classifier: Development Status :: 5 - Production/Stable
Classifier: Intended Audience :: Developers
Classifier: Intended Audience :: Education
Classifier: Intended Audience :: Science/Research
Classifier: License :: OSI Approved :: MIT License
Classifier: Natural Language :: English
Classifier: Operating System :: Unix
Classifier: Operating System :: POSIX
Classifier: Programming Language :: Python :: 2 :: Only
Classifier: Topic :: Utilities
License-File: LICENSE
Requires-Dist: python-slugify (>=1.2)
Requires-Dist: Click (>=6.7)
Requires-Dist: docker (>=4.3)
Requires-Dist: toil (==5.5.0)
Requires-Dist: requests (>=2.18)
Requires-Dist: coloredlogs (>=15.0.1)
Requires-Dist: packaging (>=21.0)
Provides-Extra: test
Requires-Dist: coverage (>=4.4.2) ; extra == 'test'
Requires-Dist: pydocstyle (>=2.1.1) ; extra == 'test'
Requires-Dist: pytest-cov (>=2.5.1) ; extra == 'test'
Requires-Dist: pytest-env (==0.6.2) ; extra == 'test'
Requires-Dist: pytest-sugar (==0.9.1) ; extra == 'test'
Requires-Dist: pylint (>=2.11.1) ; extra == 'test'
Requires-Dist: tox (==2.9.1) ; extra == 'test'
Requires-Dist: ipdb (>=0.11) ; extra == 'test'
